AUTHORS
LICENSE
README.rst
setup.py
django_linguist.egg-info/PKG-INFO
django_linguist.egg-info/SOURCES.txt
django_linguist.egg-info/dependency_links.txt
django_linguist.egg-info/not-zip-safe
django_linguist.egg-info/top_level.txt
linguist/__init__.py
linguist/admin.py
linguist/cache.py
linguist/helpers.py
linguist/metaclasses.py
linguist/mixins.py
linguist/settings.py
linguist/signals.py
linguist/utils.py
linguist/fields/__init__.py
linguist/fields/files.py
linguist/migrations/0001_initial.py
linguist/migrations/0002_auto_20170126_0355.py
linguist/migrations/__init__.py
linguist/models/__init__.py
linguist/models/base.py
linguist/models/translation.py
linguist/tests/__init__.py
linguist/tests/base.py
linguist/tests/models.py
linguist/tests/settings.py
linguist/tests/test_cache.py
linguist/tests/test_concurrency.py
linguist/tests/test_fields.py
linguist/tests/test_manager_mixin.py
linguist/tests/test_metaclass.py
linguist/tests/test_model.py
linguist/tests/test_model_mixin.py
linguist/tests/test_signals.py
linguist/tests/test_utils.py
linguist/tests/test_views.py
linguist/tests/urls.py