Metadata-Version: 2.1
Name: django-linguist
Version: 0.6.0
Summary: An application to manage translations in Django models
Home-page: http://github.com/ulule/django-linguist
Author: Gilles Fabio
Author-email: gilles.fabio@gmail.com
License: UNKNOWN
Platform: UNKNOWN
Classifier: Environment :: Web Environment
Classifier: Framework :: Django
Classifier: Intended Audience :: Developers
Classifier: License :: OSI Approved :: MIT License
Classifier: Operating System :: OS Independent
Classifier: Programming Language :: Python
Classifier: Programming Language :: Python :: 3
Classifier: Programming Language :: Python :: 3.8
Classifier: Programming Language :: Python :: 3.9
Classifier: Topic :: Software Development :: Internationalization
License-File: LICENSE
License-File: AUTHORS
